{
    "name": "EOS",
    "key": "sc",
    "measurements": [
        {
            "name": "Temperature",
            "key": "prop.temp",
            "values": [
                {
                    "key": "value",
                    "name": "Value",
                    "units": "celcius",
                    "format": "float",
                    "min": -100,
                    "max": 100,
                    "hints": {
                        "range": 1
                    }
                },
                {
                    "key": "utc",
                    "source": "timestamp",
                    "name": "Timestamp",
                    "format": "utc",
                    "hints": {
                        "domain": 1
                    }
                }
            ]
        },
      {
            "name": "Pressure",
            "key": "prop.pressure",
            "values": [
                {
                    "key": "value",
                    "name": "Value",
                    "units": "mbar",
                    "format": "float",
                    "min": 0,
                    "max": 500,
                    "hints": {
                        "range": 1
                    }
                },
                {
                    "key": "utc",
                    "source": "timestamp",
                    "name": "Timestamp",
                    "format": "utc",
                    "hints": {
                        "domain": 1
                    }
                }
            ]
        },
      {
            "name": "Humidity",
            "key": "prop.humidity",
            "values": [
                {
                    "key": "value",
                    "name": "Value",
                    "units": "%RH",
                    "format": "float",
                    "min": 0,
                    "max": 100,
                    "hints": {
                        "range": 1
                    }
                },
                {
                    "key": "utc",
                    "source": "timestamp",
                    "name": "Timestamp",
                    "format": "utc",
                    "hints": {
                        "domain": 1
                    }
                }
            ]
        },
        {
            "name": "X-Rotation",
            "key": "prop.x_rotation",
            "values": [
                {
                    "key": "value",
                    "name": "Value",
                    "units": "deg",
                    "format": "float",
                    "min": 0,
                    "max": 360,
                    "hints": {
                        "range": 1
                    }
                },
                {
                    "key": "utc",
                    "source": "timestamp",
                    "name": "Timestamp",
                    "format": "utc",
                    "hints": {
                        "domain": 1
                    }
                }
            ]
        },
        {
            "name": "Y-Rotation",
            "key": "prop.temp",
            "values": [
                {
                    "key": "value",
                    "name": "Value",
                    "units": "deg",
                    "format": "float",
                    "min": 0,
                    "max": 360,
                    "hints": {
                        "range": 1
                    }
                },
                {
                    "key": "utc",
                    "source": "timestamp",
                    "name": "Timestamp",
                    "format": "utc",
                    "hints": {
                        "domain": 1
                    }
                }
            ]
        },
        {
            "name": "Z-Rotation",
            "key": "prop.z_rotation",
            "values": [
                {
                    "key": "value",
                    "name": "Value",
                    "units": "deg",
                    "format": "float",
                    "min": 0,
                    "max": 360,
                    "hints": {
                        "range": 1
                    }
                },
                {
                    "key": "utc",
                    "source": "timestamp",
                    "name": "Timestamp",
                    "format": "utc",
                    "hints": {
                        "domain": 1
                    }
                }
            ]
        }
    ]
}